part_of_day/__init__.py
part_of_day/exceptions.py
part_of_day/part_of_day.py
part_of_day-0.5.0.dist-info/METADATA
part_of_day-0.5.0.dist-info/WHEEL
part_of_day-0.5.0.dist-info/RECORD
