Metadata-Version: 2.4
Name: part-of-day
Version: 0.5.0
Summary: This is an astral wrapper, that adds functionality for getting the part of day for a spesific datetime.
Author: mkomser
Author-email: mkomser@gmail.com
Requires-Python: >=3.9,<4.0
Classifier: Programming Language :: Python :: 3
Classifier: Programming Language :: Python :: 3.9
Classifier: Programming Language :: Python :: 3.10
Classifier: Programming Language :: Python :: 3.11
Classifier: Programming Language :: Python :: 3.12
Classifier: Programming Language :: Python :: 3.13
Classifier: Programming Language :: Python :: 3.14
Requires-Dist: astral (>=3.2,<4.0)
